MANIFEST.in
README.rst
setup.py
Products/__init__.py
Products.Faq.egg-info/PKG-INFO
Products.Faq.egg-info/SOURCES.txt
Products.Faq.egg-info/dependency_links.txt
Products.Faq.egg-info/entry_points.txt
Products.Faq.egg-info/namespace_packages.txt
Products.Faq.egg-info/not-zip-safe
Products.Faq.egg-info/requires.txt
Products.Faq.egg-info/top_level.txt
Products/Faq/LICENSE.GPL
Products/Faq/README.txt
Products/Faq/__init__.py
Products/Faq/config.py
Products/Faq/configure.zcml
Products/Faq/migrations.py
Products/Faq/modulealiases.py
Products/Faq/profiles.zcml
Products/Faq/skins.zcml
Products/Faq/testing.py
Products/Faq/usei18ndude.sh
Products/Faq/content/FaqEntry.py
Products/Faq/content/FaqFolder.py
Products/Faq/content/__init__.py
Products/Faq/content/configure.zcml
Products/Faq/content/interfaces.py
Products/Faq/locales/faq.pot
Products/Faq/locales/cs/LC_MESSAGES/faq.mo
Products/Faq/locales/cs/LC_MESSAGES/faq.po
Products/Faq/locales/de/LC_MESSAGES/faq.mo
Products/Faq/locales/de/LC_MESSAGES/faq.po
Products/Faq/locales/en/LC_MESSAGES/faq.mo
Products/Faq/locales/en/LC_MESSAGES/faq.po
Products/Faq/locales/fr/LC_MESSAGES/faq.mo
Products/Faq/locales/fr/LC_MESSAGES/faq.po
Products/Faq/locales/it/LC_MESSAGES/faq.mo
Products/Faq/locales/it/LC_MESSAGES/faq.po
Products/Faq/locales/nl/LC_MESSAGES/faq.mo
Products/Faq/locales/nl/LC_MESSAGES/faq.po
Products/Faq/profiles/default/Products.Faq.marker.txt
Products/Faq/profiles/default/factorytool.xml
Products/Faq/profiles/default/metadata.xml
Products/Faq/profiles/default/rolemap.xml
Products/Faq/profiles/default/skins.xml
Products/Faq/profiles/default/tinymce.xml
Products/Faq/profiles/default/types.xml
Products/Faq/profiles/default/types/FaqEntry.xml
Products/Faq/profiles/default/types/FaqFolder.xml
Products/Faq/skins/faq/faq_icon.gif
Products/Faq/skins/faq/faq_icon.gif.metadata
Products/Faq/skins/faq/faqentry_view.pt
Products/Faq/skins/faq/faqfolder_icon.gif
Products/Faq/skins/faq/faqfolder_icon.gif.metadata
Products/Faq/skins/faq/faqfolder_view.pt
Products/Faq/skins/faq/new.gif
Products/Faq/skins/faq/new.gif.metadata
Products/Faq/skins/faq/treeCollapsed.gif
Products/Faq/skins/faq/treeExpanded.gif
Products/Faq/tests/__init__.py
Products/Faq/tests/test_migration.py
Products/Faq/tests/test_rolemap.py
docs/HISTORY.txt