Metadata-Version: 1.1
Name: Products.Faq
Version: 1.3.2
Summary: FAQ - An AT contenttype for Plone
Home-page: https://github.com/tomgross/Products.Faq
Author: Four Digits
Author-email: info@fourdigits.nl
License: GPL
Keywords: FAQ Archetypes Plone Contenttype
Platform: UNKNOWN
Classifier: Programming Language :: Python
Classifier: Programming Language :: Python :: 2.6
Classifier: Programming Language :: Python :: 2.7
Classifier: Framework :: Plone
Classifier: Framework :: Plone :: 4.0
Classifier: Framework :: Plone :: 4.1
Classifier: Framework :: Plone :: 4.2
Classifier: Framework :: Plone :: 4.3
